urca/__init__.py
urca/common.py
urca/constants.py
urca/cpu/__init__.py
urca/cpu/block.py
urca/cpu/blocks/__init__.py
urca/cpu/blocks/present.py
urca/cpu/blocks/simeck.py
urca/cpu/blocks/simon.py
urca/cpu/blocks/speck.py
urca/gpu/__init__.py
urca/gpu/block.py
urca/gpu/blocks/__init__.py
urca/gpu/blocks/present.py
urca/gpu/blocks/simeck.py
urca/gpu/blocks/simon.py
urca/gpu/blocks/speck.py
urca-1.0.0.dist-info/licenses/LICENSE
urca-1.0.0.dist-info/METADATA
urca-1.0.0.dist-info/WHEEL
urca-1.0.0.dist-info/top_level.txt
urca-1.0.0.dist-info/RECORD
