Metadata-Version: 2.4
Name: urca
Version: 1.0.0
Summary: Unified Resource for Cryptographic Arrays
Author-email: Alessandro De Piccoli <alessandro.depiccoli@unimi.it>
Maintainer-email: Alessandro De Piccoli <alessandro.depiccoli@unimi.it>
License-Expression: BSD-3-Clause
Project-URL: Changelog, https://github.com/ale-depi/urca/blob/main/CHANGELOG.md
Project-URL: Documentation, https://ale-depi.github.io/urca/
Project-URL: Issues, https://github.com/ale-depi/urca/issues
Project-URL: Repository, https://github.com/ale-depi/urca
Classifier: Intended Audience :: Science/Research
Classifier: Operating System :: OS Independent
Classifier: Programming Language :: Python :: 3
Classifier: Topic :: Security :: Cryptography
Requires-Python: >=3.12
License-File: LICENSE
Requires-Dist: numpy
Provides-Extra: dev
Requires-Dist: commitizen; extra == "dev"
Requires-Dist: pyprojectsort; extra == "dev"
Requires-Dist: pytest; extra == "dev"
Requires-Dist: pytest-xdist; extra == "dev"
Requires-Dist: ruff; extra == "dev"
Requires-Dist: sphinx; extra == "dev"
Requires-Dist: sphinx-rtd-theme; extra == "dev"
Dynamic: license-file
